{"Status Resource":{"swagger":"2.0","info":{"description":"Status Operations","version":"1.0","title":"Status Resource","termsOfService":"urn:tos","contact":{"name":"WFAAS-LLFT@centurylink.com"},"license":{"name":"Apache 2.0","url":"http://www.apache.org/licenses/LICENSE-2.0"}},"basePath":"/","tags":[{"name":"status-resource"}],"paths":{"/status/{accountAlias}/job/{jobId}":{"get":{"tags":["status-resource"],"summary":"list","description":"list","operationId":"listUsingGET","consumes":["application/json"],"produces":["application/json"],"parameters":[{"name":"Authorization","in":"header","description":"authorization","required":true,"type":"string"},{"name":"accountAlias","in":"path","description":"accountAlias","required":true,"type":"string"},{"name":"jobId","in":"path","description":"jobId","required":true,"type":"string"},{"name":"page","in":"query","required":false,"type":"integer","format":"int32"},{"name":"size","in":"query","required":false,"type":"integer","format":"int32"}],"responses":{"200":{"description":"OK","schema":{"$ref":"#/definitions/ObjectList«Status»"}}}},"post":{"tags":["status-resource"],"summary":"create","description":"create","operationId":"createUsingPOST","consumes":["application/json"],"produces":["application/json"],"parameters":[{"name":"Authorization","in":"header","description":"authorization","required":true,"type":"string"},{"name":"accountAlias","in":"path","description":"accountAlias","required":true,"type":"string"},{"name":"jobId","in":"path","description":"jobId","required":true,"type":"string"},{"in":"body","name":"status","description":"status","required":true,"schema":{"$ref":"#/definitions/Status"}}],"responses":{"200":{"description":"OK","schema":{"$ref":"#/definitions/Status"}}}}},"/status/{accountAlias}/job/{jobId}/execution/{executionId}":{"get":{"tags":["status-resource"],"summary":"listRaw","description":"listRaw","operationId":"listRawUsingGET","consumes":["application/json"],"produces":["text/plain"],"parameters":[{"name":"Authorization","in":"header","description":"authorization","required":true,"type":"string"},{"name":"accountAlias","in":"path","description":"accountAlias","required":true,"type":"string"},{"name":"jobId","in":"path","description":"jobId","required":true,"type":"string"},{"name":"executionId","in":"path","description":"executionId","required":true,"type":"string"}],"responses":{"200":{"description":"OK"}}}},"/status/{accountAlias}/{id}":{"get":{"tags":["status-resource"],"summary":"get","description":"get","operationId":"getUsingGET","consumes":["application/json"],"produces":["application/json"],"parameters":[{"name":"Authorization","in":"header","description":"authorization","required":true,"type":"string"},{"name":"accountAlias","in":"path","description":"accountAlias","required":true,"type":"string"},{"name":"id","in":"path","description":"id","required":true,"type":"string"}],"responses":{"200":{"description":"OK","schema":{"$ref":"#/definitions/Status"}}}}}},"definitions":{"Status":{"properties":{"accountAlias":{"type":"string"},"authorization":{"type":"string"},"eventType":{"type":"string"},"executionId":{"type":"string"},"id":{"type":"string"},"jobId":{"type":"string"},"message":{"type":"object"},"notifications":{"type":"array","items":{"$ref":"#/definitions/Notification"}},"timestamp":{"type":"integer","format":"int64"}}},"ObjectList«Status»":{"properties":{"page":{"type":"integer","format":"int32"},"results":{"type":"array","items":{"$ref":"#/definitions/Status"}},"size":{"type":"integer","format":"int32"},"totalSize":{"type":"integer","format":"int64"}}},"Notification":{}}}}